nexuscontroller/__init__.py
nexuscontroller/config.py
nexuscontroller/controller.py
nexuscontroller/ui.py
nexuscontroller/utils.py
nexuscontroller/mcp/README.md
nexuscontroller/mcp/__init__.py
nexuscontroller/mcp/__main__.py
nexuscontroller/mcp/server.py
nexuscontroller-0.1.3.dist-info/METADATA
nexuscontroller-0.1.3.dist-info/WHEEL
nexuscontroller-0.1.3.dist-info/entry_points.txt
nexuscontroller-0.1.3.dist-info/licenses/LICENSE
nexuscontroller-0.1.3.dist-info/RECORD
