Metadata-Version: 2.4
Name: nexuscontroller
Version: 0.1.3
Summary: A powerful Android device control and automation platform with advanced Maestro UI testing integration and Model Context Protocol support
Author: NexusController Development Team
License: MIT
License-File: LICENSE
Requires-Python: >=3.7
Requires-Dist: pillow>=9.3.0
Requires-Dist: psutil>=5.9.0
Requires-Dist: pyaml>=21.10.1
Requires-Dist: pyyaml>=6.0
Requires-Dist: requests>=2.28.0
Requires-Dist: subprocess32>=3.5.4
Provides-Extra: advanced
Requires-Dist: numpy>=1.23.0; extra == 'advanced'
Requires-Dist: opencv-python>=4.6.0; extra == 'advanced'
Requires-Dist: pandas>=1.5.0; extra == 'advanced'
Requires-Dist: uiautomator2>=2.16.0; extra == 'advanced'
Provides-Extra: mcp
Requires-Dist: fastmcp>=2.1.1; extra == 'mcp'
